comfyui_types/__init__.py
comfyui_types/__init__.pyi
comfyui_types/_version.py
comfyui_types/export.py
comfyui_types/node.py
comfyui_types/py.typed
comfyui_types/inputs/__init__.py
comfyui_types/inputs/base.py
comfyui_types/inputs/boolean.py
comfyui_types/inputs/builtin.py
comfyui_types/inputs/choice.py
comfyui_types/inputs/float.py
comfyui_types/inputs/integer.py
comfyui_types/inputs/string.py
comfyui_types/outputs/__init__.py
comfyui_types/outputs/base.py
comfyui_types/outputs/basic.py
comfyui_types/outputs/builtin.py
comfyui_types-1.3.4.dist-info/LICENSE
comfyui_types-1.3.4.dist-info/METADATA
comfyui_types-1.3.4.dist-info/WHEEL
comfyui_types-1.3.4.dist-info/top_level.txt
comfyui_types-1.3.4.dist-info/RECORD
