Metadata-Version: 2.2
Name: comfyui_types
Version: 1.3.4
Summary: A small helper library to add types for custom ComfyUI nodes.
Author-email: Tristan Kreuziger <info@tkreuziger.com>
Project-URL: Homepage, https://github.com/tkreuziger/comfyui-types
Project-URL: Issues, https://github.com/tkreuziger/comfyui-types/issues
Classifier: Programming Language :: Python :: 3
Classifier: License :: OSI Approved :: GNU General Public License v3 (GPLv3)
Classifier: Operating System :: OS Independent
Classifier: Development Status :: 5 - Production/Stable
Requires-Python: >=3.10
License-File: LICENSE
Provides-Extra: lint
Requires-Dist: ruff<1.0,>=0.5.6; extra == "lint"
Requires-Dist: mypy-extensions>=1.0.0; extra == "lint"
Requires-Dist: mypy<2.0,>=1.11.1; extra == "lint"
Provides-Extra: build
Requires-Dist: build[virtualenv]==1.0.3; extra == "build"
Requires-Dist: twine<6.0,>=5.1.1; extra == "build"
Provides-Extra: dev
Requires-Dist: tox<5.0,>=4.23; extra == "dev"
Requires-Dist: comfyui_types[lint]; extra == "dev"
Requires-Dist: comfyui_types[build]; extra == "dev"
